.gitignore
MANIFEST.in
README.md
requirements.txt
setup.cfg
setup.py
strawberry_ratelimit/__init__.py
strawberry_ratelimit/ratelimit.py
strawberry_ratelimit.egg-info/PKG-INFO
strawberry_ratelimit.egg-info/SOURCES.txt
strawberry_ratelimit.egg-info/dependency_links.txt
strawberry_ratelimit.egg-info/requires.txt
strawberry_ratelimit.egg-info/top_level.txt