Metadata-Version: 2.1
Name: strawberry-ratelimit
Version: 1.0.1
Summary: Strawberry GraphQL Ratelimit Extension
Home-page: https://github.com/stypr/strawberry-ratelimit
Author: Harold Kim
Author-email: root@stypr.com
License: MIT
Download-URL: https://github.com/stypr/strawberry-ratelimit/archive/v1.0.1.tar.gz
Keywords: strawberry-graphql,strawberry,extension,ratelimit
Platform: UNKNOWN
Classifier: Development Status :: 5 - Production/Stable
Classifier: Intended Audience :: Developers
Classifier: License :: OSI Approved :: MIT License
Classifier: Programming Language :: Python :: 3
Classifier: Programming Language :: Python :: 3.7
Classifier: Programming Language :: Python :: 3.8
Classifier: Programming Language :: Python :: 3.9
Classifier: Programming Language :: Python :: 3.10
